{
  "01": { "kind": "photo", "src": "assets/story/01-barzan-locator-map.png",
          "caption": "Barzan, in the far northwestern corner of Erbil province.",
          "source": "locator map, The Amargi" },
  "02": { "kind": "photo", "src": "assets/story/02-abdul-salam-ii-tbilisi-1913.png",
          "caption": "Sheikh Abdul Salam II (left) with a representative of Tsar Nicholas II in Tbilisi, 1913.",
          "source": "archive" },
  "03": { "kind": "photo", "src": "assets/story/03-barzani-family-tree-ayub-barzani.png",
          "caption": "The Barzani family tree.",
          "source": "after Ayoub Barzani" },
  "04": { "kind": "photo", "src": "assets/story/04-sheikh-ahmed-mustafa-baghdad-1958.png",
          "caption": "Sheikh Ahmed and Mustafa Barzani, Baghdad, 1958.",
          "source": "archive" },
  "05": { "kind": "photo", "src": "assets/story/05-mustafa-barzani-sons-chart.png",
          "caption": "Mustafa Barzani's sons.",
          "source": "The Amargi" },
  "06": { "kind": "photo", "src": "assets/story/06-mustafa-idris-masoud-washington-1977.jpg",
          "caption": "Mustafa Barzani with Idris and Masoud, Washington, 1977.",
          "source": "archive" },
  "07": { "kind": "photo", "src": "assets/story/07-milestones-timeline-graphic.png",
          "caption": "Milestones of the House of Barzani.",
          "source": "The Amargi" },
  "w1": { "kind": "placeholder",
          "note": "Rebaz: war photograph for the First Revolt. Drop the file in assets/story/, then change this entry to kind: photo with src + caption + source." },
  "w2": { "kind": "placeholder",
          "note": "Rebaz: photograph for the 1983 genocide chapter. Drop the file in assets/story/, then change this entry to kind: photo with src + caption + source." },
  "w3": { "kind": "placeholder",
          "note": "Rebaz: video testimony or footage for the genocide chapter. Drop the file in assets/story/, then change this entry to kind: video with src + caption + source. It will be click-to-play; footage never autoplays." }
}
